siepic_forge/__init__.py
siepic_forge/component.py
siepic_forge/technology.py
siepic_forge/library/EBeam/GCs_BB.gds
siepic_forge/library/EBeam/ebeam_adiabatic_te1550.gds
siepic_forge/library/EBeam/ebeam_adiabatic_tm1550.gds
siepic_forge/library/EBeam/ebeam_bdc_te1550.gds
siepic_forge/library/EBeam/ebeam_crossing4.gds
siepic_forge/library/EBeam/ebeam_gc_te1550.gds
siepic_forge/library/EBeam/ebeam_gc_tm1550.gds
siepic_forge/library/EBeam/ebeam_routing_taper_te1550_w=500nm_to_w=3000nm_L=20um.gds
siepic_forge/library/EBeam/ebeam_routing_taper_te1550_w=500nm_to_w=3000nm_L=40um.gds
siepic_forge/library/EBeam/ebeam_splitter_swg_assist_te1310.gds
siepic_forge/library/EBeam/ebeam_splitter_swg_assist_te1550.gds
siepic_forge/library/EBeam/ebeam_terminator_te1310.gds
siepic_forge/library/EBeam/ebeam_terminator_te1550.gds
siepic_forge/library/EBeam/ebeam_terminator_tm1550.gds
siepic_forge/library/EBeam/ebeam_y_1550.gds
siepic_forge/library/EBeam/ebeam_y_adiabatic.gds
siepic_forge/library/EBeam/ebeam_y_adiabatic_500pin.gds
siepic_forge/library/EBeam/taper_si_simm_1310.gds
siepic_forge/library/EBeam/taper_si_simm_1550.gds
siepic_forge/library/EBeam_SiN/ANT_MMI_1x2_te1550_3dB_BB.gds
siepic_forge/library/EBeam_SiN/GC_SiN_TE_1310_8degOxide_BB.gds
siepic_forge/library/EBeam_SiN/GC_SiN_TE_1550_8degOxide_BB.gds
siepic_forge/library/EBeam_SiN/ULaval.gds
siepic_forge/library/EBeam_SiN/crossing_SiN_1550.gds
siepic_forge/library/EBeam_SiN/crossing_SiN_1550_extended.gds
siepic_forge/library/EBeam_SiN/crossing_horizontal.gds
siepic_forge/library/EBeam_SiN/crossing_manhattan.gds
siepic_forge/library/EBeam_SiN/ebeam_BondPad.gds
siepic_forge/library/EBeam_SiN/ebeam_DC_2-1_te895.gds
siepic_forge/library/EBeam_SiN/ebeam_DC_te895.gds
siepic_forge/library/EBeam_SiN/ebeam_Polarizer_TM_1550_UQAM.gds
siepic_forge/library/EBeam_SiN/ebeam_YBranch_895.gds
siepic_forge/library/EBeam_SiN/ebeam_gc_te895.gds
siepic_forge/library/EBeam_SiN/ebeam_terminator_SiN_1550.gds
siepic_forge-1.1.2.dist-info/licenses/LICENSE
siepic_forge-1.1.2.dist-info/METADATA
siepic_forge-1.1.2.dist-info/WHEEL
siepic_forge-1.1.2.dist-info/top_level.txt
siepic_forge-1.1.2.dist-info/RECORD
