Metadata-Version: 2.4
Name: siepic-forge
Version: 1.1.2
Summary: SiEPIC PDK implementation for PhotonForge
Author-email: "Flexcompute Inc." <info@flexcompute.com>
Project-URL: homepage, https://github.com/flexcompute/siepic-forge
Project-URL: documentation, https://github.com/flexcompute/siepic-forge
License-File: LICENSE
Requires-Dist: photonforge>=1.2.1
Provides-Extra: test
Requires-Dist: pytest>=7.2; extra == "test"
Dynamic: license-file
